netsc/__init__.py
netsc/client.py
netsc/netsc.py
netsc/server.py
netsc/struct.py
Network_Script-1.0.6.1.dist-info/LICENSE
Network_Script-1.0.6.1.dist-info/METADATA
Network_Script-1.0.6.1.dist-info/WHEEL
Network_Script-1.0.6.1.dist-info/top_level.txt
Network_Script-1.0.6.1.dist-info/RECORD
