Metadata-Version: 2.1
Name: Network-Script
Version: 1.0.6.1
Summary: Library for calling methods over sockets
Home-page: https://github.com/gaming32/Network-Script
Author: Gaming32
Author-email: gaming32i64@gmail.com
License: License :: OSI Approved :: MIT License
Platform: UNKNOWN
